[
	{
		"value":"110108011001",
		"name":"科源社区居委会"
	},
	{
		"value":"110108011002",
		"name":"科春社区居委会"
	},
	{
		"value":"110108011003",
		"name":"黄庄社区居委会"
	},
	{
		"value":"110108011004",
		"name":"科育社区居委会"
	},
	{
		"value":"110108011005",
		"name":"科馨社区居委会"
	},
	{
		"value":"110108011006",
		"name":"科煦社区居委会"
	},
	{
		"value":"110108011007",
		"name":"科汇社区居委会"
	},
	{
		"value":"110108011008",
		"name":"软件社区居委会"
	},
	{
		"value":"110108011009",
		"name":"空间社区居委会"
	},
	{
		"value":"110108011010",
		"name":"航天社区居委会"
	},
	{
		"value":"110108011011",
		"name":"东南社区居委会"
	},
	{
		"value":"110108011012",
		"name":"科星社区居委会"
	},
	{
		"value":"110108011013",
		"name":"新科祥园社区居委会"
	},
	{
		"value":"110108011014",
		"name":"西里社区居委会"
	},
	{
		"value":"110108011015",
		"name":"东里南社区居委会"
	},
	{
		"value":"110108011016",
		"name":"东里北社区居委会"
	},
	{
		"value":"110108011017",
		"name":"北里社区居委会"
	},
	{
		"value":"110108011018",
		"name":"知春里西社区居委会"
	},
	{
		"value":"110108011019",
		"name":"知春里社区居委会"
	},
	{
		"value":"110108011020",
		"name":"知春东里社区居委会"
	},
	{
		"value":"110108011023",
		"name":"白塔庵社区居委会"
	},
	{
		"value":"110108011024",
		"name":"红民村社区居委会"
	},
	{
		"value":"110108011026",
		"name":"青云北社区居委会"
	},
	{
		"value":"110108011027",
		"name":"太阳园社区居委会"
	},
	{
		"value":"110108011031",
		"name":"航勘社区居委会"
	},
	{
		"value":"110108011032",
		"name":"华清园社区居委会"
	},
	{
		"value":"110108011033",
		"name":"豪景佳苑社区居委会"
	},
	{
		"value":"110108011034",
		"name":"希格玛社区居委会"
	},
	{
		"value":"110108011035",
		"name":"航天五院社区居委会"
	},
	{
		"value":"110108011036",
		"name":"熙典华庭社区居委会"
	}
]