[
	{
		"value":"120119203201",
		"name":"丈烟台村委会"
	},
	{
		"value":"120119203202",
		"name":"北太平庄村委会"
	},
	{
		"value":"120119203203",
		"name":"永春庄村委会"
	},
	{
		"value":"120119203204",
		"name":"朱耳峪村委会"
	},
	{
		"value":"120119203205",
		"name":"荣山村委会"
	},
	{
		"value":"120119203206",
		"name":"孙各庄村委会"
	},
	{
		"value":"120119203207",
		"name":"夏家林村委会"
	},
	{
		"value":"120119203208",
		"name":"龙福寺村委会"
	},
	{
		"value":"120119203209",
		"name":"王家坎村委会"
	},
	{
		"value":"120119203210",
		"name":"朱华山村委会"
	},
	{
		"value":"120119203211",
		"name":"建新村村委会"
	},
	{
		"value":"120119203212",
		"name":"东葛岑村委会"
	},
	{
		"value":"120119203213",
		"name":"马家庄村委会"
	}
]