[
	{
		"value":"130684002200",
		"name":"撞河村民委员会"
	},
	{
		"value":"130684002201",
		"name":"乔刘樊村民委员会"
	},
	{
		"value":"130684002202",
		"name":"祁村村民委员会"
	},
	{
		"value":"130684002203",
		"name":"平安店村民委员会"
	},
	{
		"value":"130684002204",
		"name":"龚辛庄村民委员会"
	},
	{
		"value":"130684002205",
		"name":"南泽畔村民委员会"
	},
	{
		"value":"130684002206",
		"name":"松林村民委员会"
	},
	{
		"value":"130684002207",
		"name":"台中旺村民委员会"
	},
	{
		"value":"130684002208",
		"name":"李中旺村民委员会"
	},
	{
		"value":"130684002209",
		"name":"崔中旺村民委员会"
	},
	{
		"value":"130684002210",
		"name":"周中旺村民委员会"
	}
]