[
	{
		"value":"130824100203",
		"name":"北马圈子村民委员会"
	},
	{
		"value":"130824100204",
		"name":"皂沟村民委员会"
	},
	{
		"value":"130824100205",
		"name":"庄头营村民委员会"
	},
	{
		"value":"130824100206",
		"name":"西瓜园村民委员会"
	},
	{
		"value":"130824100207",
		"name":"刘院村民委员会"
	},
	{
		"value":"130824100209",
		"name":"三地沟门村民委员会"
	},
	{
		"value":"130824100210",
		"name":"岔道口村民委员会"
	},
	{
		"value":"130824100211",
		"name":"北杨树沟门村民委员会"
	},
	{
		"value":"130824100212",
		"name":"双庙村民委员会"
	},
	{
		"value":"130824100213",
		"name":"北李营村民委员会"
	},
	{
		"value":"130824100214",
		"name":"东营村民委员会"
	},
	{
		"value":"130824100217",
		"name":"安乐村民委员会"
	},
	{
		"value":"130824100218",
		"name":"铧子炉村民委员会"
	},
	{
		"value":"130824100219",
		"name":"王家沟村民委员会"
	},
	{
		"value":"130824100220",
		"name":"西台子村民委员会"
	}
]