[
	{
		"value":"140322204201",
		"name":"庄头村委会"
	},
	{
		"value":"140322204203",
		"name":"均才村委会"
	},
	{
		"value":"140322204204",
		"name":"进圭村委会"
	},
	{
		"value":"140322204206",
		"name":"东头村委会"
	},
	{
		"value":"140322204209",
		"name":"桥耳村委会"
	},
	{
		"value":"140322204211",
		"name":"宋庄村委会"
	},
	{
		"value":"140322204213",
		"name":"潘家汇村委会"
	},
	{
		"value":"140322204214",
		"name":"西潘村委会"
	},
	{
		"value":"140322204215",
		"name":"东潘村委会"
	},
	{
		"value":"140322204217",
		"name":"铜炉寨村委会"
	},
	{
		"value":"140322204221",
		"name":"李庄村委会"
	},
	{
		"value":"140322204222",
		"name":"高庄村委会"
	},
	{
		"value":"140322204224",
		"name":"羊泉村委会"
	},
	{
		"value":"140322204227",
		"name":"枣园村委会"
	}
]