[
	{
		"value":"140902005001",
		"name":"民心社区居民委员会"
	},
	{
		"value":"140902005002",
		"name":"雁门社区居民委员会"
	},
	{
		"value":"140902005201",
		"name":"解原村委会"
	},
	{
		"value":"140902005202",
		"name":"北赵村委会"
	},
	{
		"value":"140902005203",
		"name":"小奇村委会"
	},
	{
		"value":"140902005204",
		"name":"六石村委会"
	},
	{
		"value":"140902005205",
		"name":"豆槐村委会"
	},
	{
		"value":"140902005206",
		"name":"佐城村委会"
	},
	{
		"value":"140902005207",
		"name":"东社村委会"
	},
	{
		"value":"140902005208",
		"name":"新路村委会"
	},
	{
		"value":"140902005209",
		"name":"流江村委会"
	},
	{
		"value":"140902005210",
		"name":"乔村村委会"
	},
	{
		"value":"140902005212",
		"name":"大庄村委会"
	},
	{
		"value":"140902005213",
		"name":"上社村委会"
	},
	{
		"value":"140902005214",
		"name":"西冯城村委会"
	},
	{
		"value":"140902005215",
		"name":"东冯城村委会"
	},
	{
		"value":"140902005216",
		"name":"土陵桥村委会"
	},
	{
		"value":"140902005217",
		"name":"北张村委会"
	}
]