[
	{
		"value":"141026100003",
		"name":"城墙岭社区居委会"
	},
	{
		"value":"141026100004",
		"name":"月亮湾社区居委会"
	},
	{
		"value":"141026100005",
		"name":"清华园社区居委会"
	},
	{
		"value":"141026100006",
		"name":"文欣社区居委会"
	},
	{
		"value":"141026100200",
		"name":"府城村民委员会"
	},
	{
		"value":"141026100202",
		"name":"桃寨村民委员会"
	},
	{
		"value":"141026100203",
		"name":"第五村民委员会"
	},
	{
		"value":"141026100204",
		"name":"孔村村民委员会"
	},
	{
		"value":"141026100205",
		"name":"神南村民委员会"
	},
	{
		"value":"141026100206",
		"name":"高壁村民委员会"
	},
	{
		"value":"141026100209",
		"name":"飞岭村民委员会"
	},
	{
		"value":"141026100210",
		"name":"桃曲村民委员会"
	},
	{
		"value":"141026100211",
		"name":"义唐村民委员会"
	},
	{
		"value":"141026100220",
		"name":"上梯村民委员会"
	},
	{
		"value":"141026100221",
		"name":"凤池村民委员会"
	},
	{
		"value":"141026100222",
		"name":"小黄村民委员会"
	},
	{
		"value":"141026100223",
		"name":"三交村民委员会"
	},
	{
		"value":"141026100224",
		"name":"李垣村民委员会"
	}
]