[
	{
		"value":"150221107004",
		"name":"农林街居委会"
	},
	{
		"value":"150221107200",
		"name":"火盘村委会"
	},
	{
		"value":"150221107201",
		"name":"西湾村委会"
	},
	{
		"value":"150221107202",
		"name":"庙湾村委会"
	},
	{
		"value":"150221107203",
		"name":"后湾村委会"
	},
	{
		"value":"150221107204",
		"name":"东湾村委会"
	},
	{
		"value":"150221107205",
		"name":"小城村委会"
	},
	{
		"value":"150221107206",
		"name":"纳太村委会"
	},
	{
		"value":"150221107207",
		"name":"沙兵崖村委会"
	},
	{
		"value":"150221107208",
		"name":"北只图村委会"
	},
	{
		"value":"150221107209",
		"name":"威俊村委会"
	},
	{
		"value":"150221107210",
		"name":"此老气村委会"
	},
	{
		"value":"150221107211",
		"name":"板申气村委会"
	},
	{
		"value":"150221107212",
		"name":"马留村委会"
	},
	{
		"value":"150221107400",
		"name":"土默特右旗新型工业园区管理委员会社区"
	}
]