[
	{
		"value":"150825100001",
		"name":"查干乌林社区"
	},
	{
		"value":"150825100002",
		"name":"惠民社区"
	},
	{
		"value":"150825100003",
		"name":"塞上社区"
	},
	{
		"value":"150825100004",
		"name":"蓝天社区"
	},
	{
		"value":"150825100005",
		"name":"纳林社区"
	},
	{
		"value":"150825100200",
		"name":"友联村委会"
	},
	{
		"value":"150825100201",
		"name":"东升村委会"
	},
	{
		"value":"150825100202",
		"name":"团结村委会"
	},
	{
		"value":"150825100203",
		"name":"浩日格嘎查"
	},
	{
		"value":"150825100204",
		"name":"朱斯木尔嘎查"
	},
	{
		"value":"150825100205",
		"name":"那仁乌拉嘎查"
	},
	{
		"value":"150825100206",
		"name":"宝力格嘎查"
	},
	{
		"value":"150825100207",
		"name":"乌兰嘎查"
	},
	{
		"value":"150825100208",
		"name":"蒙汉村委会"
	},
	{
		"value":"150825100209",
		"name":"三支渠村委会"
	},
	{
		"value":"150825100210",
		"name":"五支渠村委会"
	}
]