[
	{
		"value":"152221108001",
		"name":"兴安社区居委会"
	},
	{
		"value":"152221108002",
		"name":"白辛社区居委会"
	},
	{
		"value":"152221108200",
		"name":"兴安村委会"
	},
	{
		"value":"152221108201",
		"name":"全胜村委会"
	},
	{
		"value":"152221108202",
		"name":"义新村委会"
	},
	{
		"value":"152221108203",
		"name":"景阳村委会"
	},
	{
		"value":"152221108204",
		"name":"全发村委会"
	},
	{
		"value":"152221108205",
		"name":"双花村委会"
	},
	{
		"value":"152221108206",
		"name":"乌兰村委会"
	},
	{
		"value":"152221108207",
		"name":"德富村委会"
	},
	{
		"value":"152221108208",
		"name":"双胜村委会"
	},
	{
		"value":"152221108209",
		"name":"俄体村委会"
	},
	{
		"value":"152221108210",
		"name":"团结村委会"
	},
	{
		"value":"152221108211",
		"name":"齐心村委会"
	},
	{
		"value":"152221108212",
		"name":"永远村委会"
	},
	{
		"value":"152221108213",
		"name":"白音村委会"
	}
]