[
	{
		"value":"210115109200",
		"name":"三西村委会"
	},
	{
		"value":"210115109201",
		"name":"妈妈街村委会"
	},
	{
		"value":"210115109202",
		"name":"七南村委会"
	},
	{
		"value":"210115109203",
		"name":"七北村委会"
	},
	{
		"value":"210115109204",
		"name":"沙西村委会"
	},
	{
		"value":"210115109205",
		"name":"三南村委会"
	},
	{
		"value":"210115109206",
		"name":"沙东村委会"
	},
	{
		"value":"210115109207",
		"name":"三东村委会"
	},
	{
		"value":"210115109208",
		"name":"三北村委会"
	},
	{
		"value":"210115109209",
		"name":"后老薄村委会"
	},
	{
		"value":"210115109210",
		"name":"双树坨村委会"
	},
	{
		"value":"210115109211",
		"name":"老观坨村委会"
	},
	{
		"value":"210115109212",
		"name":"大兰坨村委会"
	},
	{
		"value":"210115109213",
		"name":"肖兰坨村委会"
	},
	{
		"value":"210115109214",
		"name":"大岗子村委会"
	},
	{
		"value":"210115109215",
		"name":"肖北社区村民委员会"
	},
	{
		"value":"210115109216",
		"name":"肖东社区村民委员会"
	},
	{
		"value":"210115109217",
		"name":"肖南社区村民委员会"
	}
]