[
	{
		"value":"210781107200",
		"name":"右东村民委员会"
	},
	{
		"value":"210781107201",
		"name":"右西村民委员会"
	},
	{
		"value":"210781107202",
		"name":"西彭村民委员会"
	},
	{
		"value":"210781107203",
		"name":"小马东张村民委员会"
	},
	{
		"value":"210781107204",
		"name":"西网东网村民委员会"
	},
	{
		"value":"210781107205",
		"name":"大康村民委员会"
	},
	{
		"value":"210781107206",
		"name":"苗屯昌盛村民委员会"
	},
	{
		"value":"210781107207",
		"name":"大王大黄村民委员会"
	},
	{
		"value":"210781107208",
		"name":"大马村民委员会"
	},
	{
		"value":"210781107209",
		"name":"小黄东岳村民委员会"
	}
]