[
	{
		"value":"220203102001",
		"name":"江密峰社区"
	},
	{
		"value":"220203102200",
		"name":"江密峰村"
	},
	{
		"value":"220203102201",
		"name":"振兴村"
	},
	{
		"value":"220203102202",
		"name":"西三家子村"
	},
	{
		"value":"220203102203",
		"name":"双桠山村"
	},
	{
		"value":"220203102204",
		"name":"东三家子村"
	},
	{
		"value":"220203102205",
		"name":"东光村"
	},
	{
		"value":"220203102207",
		"name":"胜利村"
	},
	{
		"value":"220203102209",
		"name":"南沙村"
	},
	{
		"value":"220203102210",
		"name":"榆树沟村"
	},
	{
		"value":"220203102211",
		"name":"小川村"
	},
	{
		"value":"220203102212",
		"name":"望马沟村"
	},
	{
		"value":"220203102214",
		"name":"石咀子村"
	},
	{
		"value":"220203102215",
		"name":"大茶棚村"
	},
	{
		"value":"220203102216",
		"name":"下江密峰村"
	},
	{
		"value":"220203102217",
		"name":"黄金村"
	},
	{
		"value":"220203102218",
		"name":"金刚村"
	},
	{
		"value":"220203102219",
		"name":"龙家村"
	},
	{
		"value":"220203102220",
		"name":"新道村"
	},
	{
		"value":"220203102221",
		"name":"新山村"
	},
	{
		"value":"220203102222",
		"name":"夹信子村"
	},
	{
		"value":"220203102223",
		"name":"崔家屯村"
	},
	{
		"value":"220203102224",
		"name":"东方红村"
	},
	{
		"value":"220203102225",
		"name":"桥南村"
	},
	{
		"value":"220203102226",
		"name":"安山村"
	},
	{
		"value":"220203102227",
		"name":"北沙村"
	},
	{
		"value":"220203102228",
		"name":"唐房村"
	},
	{
		"value":"220203102229",
		"name":"蚕场村"
	},
	{
		"value":"220203102230",
		"name":"蛤蟆河子村"
	},
	{
		"value":"220203102231",
		"name":"中沙村"
	},
	{
		"value":"220203102232",
		"name":"高家洼子村"
	}
]