[
	{
		"value":"220524100204",
		"name":"砬门子村"
	},
	{
		"value":"220524100205",
		"name":"复兴村"
	},
	{
		"value":"220524100206",
		"name":"白家村"
	},
	{
		"value":"220524100207",
		"name":"杨家炉村"
	},
	{
		"value":"220524100208",
		"name":"宋油房村"
	},
	{
		"value":"220524100209",
		"name":"四大门村"
	},
	{
		"value":"220524100210",
		"name":"包大桥村"
	},
	{
		"value":"220524100212",
		"name":"陈家村"
	},
	{
		"value":"220524100213",
		"name":"复新村"
	},
	{
		"value":"220524100214",
		"name":"联合村"
	},
	{
		"value":"220524100215",
		"name":"三仙夹村"
	},
	{
		"value":"220524100216",
		"name":"中安村"
	},
	{
		"value":"220524100220",
		"name":"柳树村"
	},
	{
		"value":"220524100221",
		"name":"大郑家村"
	},
	{
		"value":"220524100222",
		"name":"新发东村"
	},
	{
		"value":"220524100223",
		"name":"新发西村"
	},
	{
		"value":"220524100225",
		"name":"里仁村"
	},
	{
		"value":"220524100226",
		"name":"邵大院村"
	},
	{
		"value":"220524100227",
		"name":"前仙人村"
	},
	{
		"value":"220524100228",
		"name":"后仙人村"
	},
	{
		"value":"220524100229",
		"name":"吉祥村"
	},
	{
		"value":"220524100230",
		"name":"水背村"
	},
	{
		"value":"220524100231",
		"name":"永丰村"
	}
]