[
	{
		"value":"320382121201",
		"name":"车辐山村委会"
	},
	{
		"value":"320382121202",
		"name":"车前村委会"
	},
	{
		"value":"320382121203",
		"name":"新庄村委会"
	},
	{
		"value":"320382121204",
		"name":"刘楼村委会"
	},
	{
		"value":"320382121205",
		"name":"官厢村委会"
	},
	{
		"value":"320382121206",
		"name":"红光村委会"
	},
	{
		"value":"320382121207",
		"name":"杨滩村委会"
	},
	{
		"value":"320382121208",
		"name":"运西村委会"
	},
	{
		"value":"320382121209",
		"name":"友好村委会"
	},
	{
		"value":"320382121210",
		"name":"任庄村委会"
	},
	{
		"value":"320382121211",
		"name":"山南村委会"
	},
	{
		"value":"320382121212",
		"name":"埠上村委会"
	},
	{
		"value":"320382121213",
		"name":"梁河村委会"
	},
	{
		"value":"320382121214",
		"name":"明远村委会"
	},
	{
		"value":"320382121215",
		"name":"龙湖村委会"
	},
	{
		"value":"320382121216",
		"name":"潘楼村委会"
	}
]