[
	{
		"value":"330483004001",
		"name":"高桥社区居委会"
	},
	{
		"value":"330483004200",
		"name":"高桥村村委会"
	},
	{
		"value":"330483004201",
		"name":"落晚村村委会"
	},
	{
		"value":"330483004202",
		"name":"楼下角村村委会"
	},
	{
		"value":"330483004203",
		"name":"亭桥村村委会"
	},
	{
		"value":"330483004204",
		"name":"永安村村委会"
	},
	{
		"value":"330483004205",
		"name":"范桥村村委会"
	},
	{
		"value":"330483004206",
		"name":"毛水浜村村委会"
	},
	{
		"value":"330483004207",
		"name":"三村村村委会"
	},
	{
		"value":"330483004208",
		"name":"越丰村村委会"
	},
	{
		"value":"330483004209",
		"name":"新丰村村委会"
	},
	{
		"value":"330483004210",
		"name":"迎丰村村委会"
	},
	{
		"value":"330483004211",
		"name":"骑力村村委会"
	},
	{
		"value":"330483004212",
		"name":"湘庄村村委会"
	},
	{
		"value":"330483004213",
		"name":"龙南村村委会"
	},
	{
		"value":"330483004214",
		"name":"漕泾村村委会"
	}
]