[
	{
		"value":"330681110001",
		"name":"兰台社区"
	},
	{
		"value":"330681110002",
		"name":"赵家社区"
	},
	{
		"value":"330681110212",
		"name":"花明泉村委会"
	},
	{
		"value":"330681110215",
		"name":"上京村委会"
	},
	{
		"value":"330681110220",
		"name":"潘村委会"
	},
	{
		"value":"330681110240",
		"name":"相泉村委会"
	},
	{
		"value":"330681110247",
		"name":"东溪村委会"
	},
	{
		"value":"330681110248",
		"name":"宣家山村委会"
	},
	{
		"value":"330681110249",
		"name":"新绛霞村委会"
	},
	{
		"value":"330681110250",
		"name":"保安新村委会"
	},
	{
		"value":"330681110251",
		"name":"大柳仙村委会"
	},
	{
		"value":"330681110252",
		"name":"泉畈村委会"
	},
	{
		"value":"330681110253",
		"name":"榧王村委会"
	},
	{
		"value":"330681110254",
		"name":"东庄村委会"
	}
]