[
	{
		"value":"341502101001",
		"name":"街道居委会"
	},
	{
		"value":"341502101200",
		"name":"陈滩村委会"
	},
	{
		"value":"341502101201",
		"name":"龙滩村委会"
	},
	{
		"value":"341502101202",
		"name":"黄台村委会"
	},
	{
		"value":"341502101203",
		"name":"陈台村委会"
	},
	{
		"value":"341502101204",
		"name":"孙长郢村委会"
	},
	{
		"value":"341502101205",
		"name":"感应寺村委会"
	},
	{
		"value":"341502101206",
		"name":"胡楼村委会"
	},
	{
		"value":"341502101207",
		"name":"李大楼村委会"
	},
	{
		"value":"341502101208",
		"name":"十字路村委会"
	},
	{
		"value":"341502101209",
		"name":"崔店村委会"
	},
	{
		"value":"341502101210",
		"name":"黄店村委会"
	},
	{
		"value":"341502101211",
		"name":"高皇村委会"
	}
]