[
	{
		"value":"350725203202",
		"name":"澄源村委会"
	},
	{
		"value":"350725203203",
		"name":"前山村委会"
	},
	{
		"value":"350725203204",
		"name":"前村村委会"
	},
	{
		"value":"350725203205",
		"name":"林山村委会"
	},
	{
		"value":"350725203206",
		"name":"香溪村委会"
	},
	{
		"value":"350725203207",
		"name":"富垅村委会"
	},
	{
		"value":"350725203208",
		"name":"叶甘地村委会"
	},
	{
		"value":"350725203209",
		"name":"路下村委会"
	},
	{
		"value":"350725203210",
		"name":"上温洋村委会"
	},
	{
		"value":"350725203211",
		"name":"黄坦村委会"
	},
	{
		"value":"350725203212",
		"name":"石壁村委会"
	},
	{
		"value":"350725203213",
		"name":"下温洋村委会"
	},
	{
		"value":"350725203214",
		"name":"上洋村委会"
	},
	{
		"value":"350725203215",
		"name":"北斗村委会"
	},
	{
		"value":"350725203216",
		"name":"黄岭村委会"
	},
	{
		"value":"350725203217",
		"name":"星溪头村委会"
	},
	{
		"value":"350725203218",
		"name":"坑里村委会"
	},
	{
		"value":"350725203219",
		"name":"新康村委会"
	},
	{
		"value":"350725203220",
		"name":"赤溪村委会"
	},
	{
		"value":"350725203221",
		"name":"牛途村委会"
	},
	{
		"value":"350725203222",
		"name":"大梨溪村委会"
	},
	{
		"value":"350725203223",
		"name":"双新村委会"
	}
]