[
	{
		"value":"360826200001",
		"name":"松石居委会"
	},
	{
		"value":"360826200200",
		"name":"石山村委会"
	},
	{
		"value":"360826200201",
		"name":"良友村委会"
	},
	{
		"value":"360826200202",
		"name":"冻边村委会"
	},
	{
		"value":"360826200203",
		"name":"社背村委会"
	},
	{
		"value":"360826200204",
		"name":"上居村委会"
	},
	{
		"value":"360826200205",
		"name":"老张家村委会"
	},
	{
		"value":"360826200206",
		"name":"良潭村委会"
	},
	{
		"value":"360826200207",
		"name":"齐塘村委会"
	},
	{
		"value":"360826200208",
		"name":"洲下村委会"
	}
]