[
	{
		"value":"361027104200",
		"name":"合市村委会"
	},
	{
		"value":"361027104201",
		"name":"大耿村委会"
	},
	{
		"value":"361027104202",
		"name":"龚家村委会"
	},
	{
		"value":"361027104203",
		"name":"塘霞村委会"
	},
	{
		"value":"361027104204",
		"name":"岐岭村委会"
	},
	{
		"value":"361027104205",
		"name":"斛塘村委会"
	},
	{
		"value":"361027104206",
		"name":"联桥村委会"
	},
	{
		"value":"361027104207",
		"name":"湖坊村委会"
	},
	{
		"value":"361027104208",
		"name":"坪上村委会"
	},
	{
		"value":"361027104209",
		"name":"崇麓村委会"
	},
	{
		"value":"361027104210",
		"name":"肖公村委会"
	},
	{
		"value":"361027104211",
		"name":"田南村委会"
	},
	{
		"value":"361027104212",
		"name":"车门村委会"
	},
	{
		"value":"361027104213",
		"name":"杭桥村委会"
	},
	{
		"value":"361027104214",
		"name":"凤凰山村委会"
	}
]