[
	{
		"value":"370614005001",
		"name":"半岛兰庭社区居民委员会"
	},
	{
		"value":"370614005201",
		"name":"南王村委会"
	},
	{
		"value":"370614005202",
		"name":"团结村委会"
	},
	{
		"value":"370614005203",
		"name":"羽山张家村委会"
	},
	{
		"value":"370614005204",
		"name":"羽山大丁家村委会"
	},
	{
		"value":"370614005205",
		"name":"羽山小丁家村委会"
	},
	{
		"value":"370614005206",
		"name":"姚庄村委会"
	},
	{
		"value":"370614005207",
		"name":"依庄村委会"
	},
	{
		"value":"370614005208",
		"name":"枣林店村委会"
	},
	{
		"value":"370614005209",
		"name":"窑上村委会"
	},
	{
		"value":"370614005210",
		"name":"贯里村委会"
	},
	{
		"value":"370614005211",
		"name":"邢家村委会"
	},
	{
		"value":"370614005212",
		"name":"北王村委会"
	},
	{
		"value":"370614005213",
		"name":"寨里村委会"
	},
	{
		"value":"370614005214",
		"name":"头包家村委会"
	},
	{
		"value":"370614005215",
		"name":"二包家村委会"
	},
	{
		"value":"370614005216",
		"name":"三包家村委会"
	},
	{
		"value":"370614005217",
		"name":"二十埠村委会"
	},
	{
		"value":"370614005218",
		"name":"大院村委会"
	},
	{
		"value":"370614005219",
		"name":"磕王村委会"
	},
	{
		"value":"370614005220",
		"name":"磕刘村委会"
	},
	{
		"value":"370614005221",
		"name":"磕刘二村委会"
	},
	{
		"value":"370614005222",
		"name":"宿驾埠村委会"
	},
	{
		"value":"370614005223",
		"name":"泊子王家村委会"
	},
	{
		"value":"370614005224",
		"name":"泊子宋家村委会"
	},
	{
		"value":"370614005225",
		"name":"西沟方家村委会"
	},
	{
		"value":"370614005226",
		"name":"班家庄村委会"
	},
	{
		"value":"370614005227",
		"name":"北八甲村委会"
	},
	{
		"value":"370614005228",
		"name":"泥河村委会"
	},
	{
		"value":"370614005229",
		"name":"大宁家村委会"
	},
	{
		"value":"370614005230",
		"name":"小宁家村委会"
	},
	{
		"value":"370614005231",
		"name":"大王家村委会"
	},
	{
		"value":"370614005232",
		"name":"郭家沟村委会"
	},
	{
		"value":"370614005233",
		"name":"徐家沟村委会"
	},
	{
		"value":"370614005234",
		"name":"杏王村委会"
	},
	{
		"value":"370614005235",
		"name":"杏吕村委会"
	},
	{
		"value":"370614005236",
		"name":"范家店村委会"
	},
	{
		"value":"370614005237",
		"name":"魏家庄村委会"
	},
	{
		"value":"370614005238",
		"name":"平山吴家村委会"
	},
	{
		"value":"370614005239",
		"name":"平山刘家村委会"
	},
	{
		"value":"370614005240",
		"name":"平山杨家村委会"
	},
	{
		"value":"370614005241",
		"name":"位张村委会"
	},
	{
		"value":"370614005242",
		"name":"位吴村委会"
	},
	{
		"value":"370614005243",
		"name":"位骆村委会"
	},
	{
		"value":"370614005244",
		"name":"南八甲村委会"
	},
	{
		"value":"370614005245",
		"name":"柳行村委会"
	},
	{
		"value":"370614005246",
		"name":"七里庄村委会"
	},
	{
		"value":"370614005247",
		"name":"石庙张家村委会"
	},
	{
		"value":"370614005248",
		"name":"石庙石家村委会"
	},
	{
		"value":"370614005249",
		"name":"苗家沟村委会"
	},
	{
		"value":"370614005250",
		"name":"后韩村委会"
	},
	{
		"value":"370614005251",
		"name":"韩王村委会"
	},
	{
		"value":"370614005252",
		"name":"牛山杨家村委会"
	},
	{
		"value":"370614005253",
		"name":"大李家村委会"
	},
	{
		"value":"370614005254",
		"name":"石庙周家村委会"
	},
	{
		"value":"370614005255",
		"name":"伍庄村委会"
	},
	{
		"value":"370614005256",
		"name":"姜家沟村委会"
	},
	{
		"value":"370614005257",
		"name":"雨山刘家村委会"
	}
]