[
	{
		"value":"370704004201",
		"name":"河北郎郡庄村委会"
	},
	{
		"value":"370704004202",
		"name":"张疃村委会"
	},
	{
		"value":"370704004203",
		"name":"祥疃村委会"
	},
	{
		"value":"370704004204",
		"name":"李家水坡村委会"
	},
	{
		"value":"370704004205",
		"name":"任家水坡村委会"
	},
	{
		"value":"370704004206",
		"name":"洼里村委会"
	},
	{
		"value":"370704004207",
		"name":"侯家庄村委会"
	},
	{
		"value":"370704004208",
		"name":"蔡家石埠村委会"
	},
	{
		"value":"370704004209",
		"name":"张家石埠村委会"
	},
	{
		"value":"370704004210",
		"name":"王家石埠村委会"
	},
	{
		"value":"370704004211",
		"name":"于家石埠村委会"
	},
	{
		"value":"370704004212",
		"name":"沙埠村委会"
	},
	{
		"value":"370704004213",
		"name":"西王松村委会"
	},
	{
		"value":"370704004214",
		"name":"高陵官庄村委会"
	},
	{
		"value":"370704004215",
		"name":"荒里村委会"
	},
	{
		"value":"370704004216",
		"name":"东村村委会"
	},
	{
		"value":"370704004217",
		"name":"南店村委会"
	},
	{
		"value":"370704004218",
		"name":"西曹庄村委会"
	},
	{
		"value":"370704004219",
		"name":"罗家宅子村委会"
	},
	{
		"value":"370704004220",
		"name":"东王松一村村委会"
	},
	{
		"value":"370704004221",
		"name":"东王松二村村委会"
	},
	{
		"value":"370704004222",
		"name":"东王松三村村委会"
	},
	{
		"value":"370704004223",
		"name":"东王松四村村委会"
	},
	{
		"value":"370704004224",
		"name":"建华村村委会"
	},
	{
		"value":"370704004225",
		"name":"兴华村委会"
	},
	{
		"value":"370704004226",
		"name":"北坡子村委会"
	},
	{
		"value":"370704004227",
		"name":"流戈庄村委会"
	},
	{
		"value":"370704004228",
		"name":"宋家村委会"
	},
	{
		"value":"370704004229",
		"name":"东苏村委会"
	},
	{
		"value":"370704004230",
		"name":"前苏村委会"
	},
	{
		"value":"370704004231",
		"name":"张家村委会"
	},
	{
		"value":"370704004232",
		"name":"滕家庄子村委会"
	},
	{
		"value":"370704004233",
		"name":"南王皋村委会"
	},
	{
		"value":"370704004234",
		"name":"北王皋村委会"
	},
	{
		"value":"370704004235",
		"name":"东曹村村委会"
	},
	{
		"value":"370704004236",
		"name":"西曹村村委会"
	},
	{
		"value":"370704004237",
		"name":"前曹村村委会"
	},
	{
		"value":"370704004238",
		"name":"后曹村村委会"
	},
	{
		"value":"370704004239",
		"name":"港涘村委会"
	},
	{
		"value":"370704004240",
		"name":"营子村委会"
	},
	{
		"value":"370704004241",
		"name":"河湾村委会"
	},
	{
		"value":"370704004242",
		"name":"大尚庄村委会"
	},
	{
		"value":"370704004243",
		"name":"小尚庄村委会"
	},
	{
		"value":"370704004244",
		"name":"石坑村委会"
	},
	{
		"value":"370704004245",
		"name":"吴家庄村委会"
	},
	{
		"value":"370704004246",
		"name":"东埠郎郡庄村委会"
	},
	{
		"value":"370704004247",
		"name":"圈子郎郡庄村委会"
	},
	{
		"value":"370704004248",
		"name":"庙东郎郡庄村委会"
	},
	{
		"value":"370704004249",
		"name":"庙后郎郡庄村委会"
	},
	{
		"value":"370704004250",
		"name":"河南郎郡庄村委会"
	},
	{
		"value":"370704004251",
		"name":"葫芦埠李家村委会"
	},
	{
		"value":"370704004252",
		"name":"葫芦埠梁家村委会"
	},
	{
		"value":"370704004253",
		"name":"葫芦埠韩家村委会"
	},
	{
		"value":"370704004254",
		"name":"田家庄子村委会"
	},
	{
		"value":"370704004255",
		"name":"小庄子村委会"
	},
	{
		"value":"370704004256",
		"name":"石龙官庄村委会"
	},
	{
		"value":"370704004257",
		"name":"葫芦埠肖家村委会"
	},
	{
		"value":"370704004258",
		"name":"葫芦埠于家村委会"
	},
	{
		"value":"370704004259",
		"name":"王家庄子村委会"
	}
]