[
	{
		"value":"370705003003",
		"name":"樱园社区居民委员会"
	},
	{
		"value":"370705003007",
		"name":"梨园社区居民委员会"
	},
	{
		"value":"370705003008",
		"name":"樱南社区居民委员会"
	},
	{
		"value":"370705003009",
		"name":"樱北社区居民委员会"
	},
	{
		"value":"370705003010",
		"name":"西英社区居民委员会"
	},
	{
		"value":"370705003011",
		"name":"庄家社区居民委员会"
	},
	{
		"value":"370705003014",
		"name":"张家庄子社区居民委员会"
	},
	{
		"value":"370705003015",
		"name":"九龙山社区居民委员会"
	},
	{
		"value":"370705003017",
		"name":"龙源社区居民委员会"
	},
	{
		"value":"370705003018",
		"name":"栾家社区居民委员会"
	}
]