[
	{
		"value":"410602100001",
		"name":"北街社区居民委员会"
	},
	{
		"value":"410602100002",
		"name":"西街社区居民委员会"
	},
	{
		"value":"410602100003",
		"name":"教场社区居民委员会"
	},
	{
		"value":"410602100004",
		"name":"杨庄社区居民委员会"
	},
	{
		"value":"410602100005",
		"name":"王家荒社区居民委员会"
	},
	{
		"value":"410602100006",
		"name":"孙圣沟社区居民委员会"
	},
	{
		"value":"410602100007",
		"name":"中马驹河社区居民委员会"
	},
	{
		"value":"410602100008",
		"name":"东马驹河社区居民委员会"
	},
	{
		"value":"410602100009",
		"name":"韩林涧社区居民委员会"
	},
	{
		"value":"410602100010",
		"name":"曹家社区居民委员会"
	},
	{
		"value":"410602100011",
		"name":"南街社区居民委员会"
	},
	{
		"value":"410602100012",
		"name":"东街社区居民委员会"
	},
	{
		"value":"410602100204",
		"name":"北杨邑村民委员会"
	},
	{
		"value":"410602100206",
		"name":"龙卧村民委员会"
	},
	{
		"value":"410602100207",
		"name":"西杨邑村民委员会"
	},
	{
		"value":"410602100208",
		"name":"东杨邑村民委员会"
	},
	{
		"value":"410602100209",
		"name":"东头村民委员会"
	},
	{
		"value":"410602100210",
		"name":"郭家岗村民委员会"
	},
	{
		"value":"410602100211",
		"name":"南杨邑村民委员会"
	},
	{
		"value":"410602100212",
		"name":"毕吕寨村民委员会"
	},
	{
		"value":"410602100213",
		"name":"大吕寨村民委员会"
	},
	{
		"value":"410602100214",
		"name":"贾吕寨村民委员会"
	},
	{
		"value":"410602100215",
		"name":"窦马庄村民委员会"
	},
	{
		"value":"410602100216",
		"name":"王吕寨村民委员会"
	},
	{
		"value":"410602100217",
		"name":"杨吕寨村民委员会"
	},
	{
		"value":"410602100218",
		"name":"郭吕寨村民委员会"
	},
	{
		"value":"410602100219",
		"name":"焦家沟村民委员会"
	},
	{
		"value":"410602100220",
		"name":"前蜀村民委员会"
	},
	{
		"value":"410602100221",
		"name":"后蜀村民委员会"
	},
	{
		"value":"410602100222",
		"name":"龙宫村民委员会"
	},
	{
		"value":"410602100223",
		"name":"王马庄村民委员会"
	},
	{
		"value":"410602100224",
		"name":"古楼河村民委员会"
	},
	{
		"value":"410602100225",
		"name":"梁峪村民委员会"
	},
	{
		"value":"410602100227",
		"name":"石碑头村民委员会"
	},
	{
		"value":"410602100228",
		"name":"梨林头村民委员会"
	},
	{
		"value":"410602100229",
		"name":"寺弯村民委员会"
	},
	{
		"value":"410602100231",
		"name":"郝家荒村民委员会"
	},
	{
		"value":"410602100232",
		"name":"张家荒村民委员会"
	},
	{
		"value":"410602100234",
		"name":"井坡村民委员会"
	},
	{
		"value":"410602100235",
		"name":"西马驹河村民委员会"
	},
	{
		"value":"410602100238",
		"name":"赵家荒村民委员会"
	},
	{
		"value":"410602100239",
		"name":"李家荒村民委员会"
	},
	{
		"value":"410602100241",
		"name":"中杨邑村民委员会"
	},
	{
		"value":"410602100243",
		"name":"贾家村民委员会"
	}
]