[
	{
		"value":"411103101001",
		"name":"李村居民委员会"
	},
	{
		"value":"411103101002",
		"name":"中村居民委员会"
	},
	{
		"value":"411103101003",
		"name":"卓村居民委员会"
	},
	{
		"value":"411103101004",
		"name":"后郑居民委员会"
	},
	{
		"value":"411103101201",
		"name":"三周村村民委员会"
	},
	{
		"value":"411103101202",
		"name":"孟庙村村民委员会"
	},
	{
		"value":"411103101203",
		"name":"张仁庄村村民委员会"
	},
	{
		"value":"411103101204",
		"name":"关徐村村民委员会"
	},
	{
		"value":"411103101205",
		"name":"张店村村民委员会"
	},
	{
		"value":"411103101206",
		"name":"薛赵村村民委员会"
	},
	{
		"value":"411103101207",
		"name":"西营村村民委员会"
	},
	{
		"value":"411103101208",
		"name":"闫陶村村民委员会"
	},
	{
		"value":"411103101209",
		"name":"潘东村村民委员会"
	},
	{
		"value":"411103101210",
		"name":"潘西村村民委员会"
	},
	{
		"value":"411103101211",
		"name":"潘北村村民委员会"
	},
	{
		"value":"411103101212",
		"name":"拦河刘村村民委员会"
	},
	{
		"value":"411103101213",
		"name":"王店村村民委员会"
	},
	{
		"value":"411103101214",
		"name":"袁黄村村民委员会"
	},
	{
		"value":"411103101215",
		"name":"蒋堂村村民委员会"
	},
	{
		"value":"411103101216",
		"name":"沈赵村村民委员会"
	},
	{
		"value":"411103101217",
		"name":"杜李村村民委员会"
	},
	{
		"value":"411103101226",
		"name":"路堂村村民委员会"
	},
	{
		"value":"411103101227",
		"name":"八里村村民委员会"
	},
	{
		"value":"411103101228",
		"name":"何庄村村民委员会"
	},
	{
		"value":"411103101229",
		"name":"坡陈村村民委员会"
	},
	{
		"value":"411103101230",
		"name":"新郑村村民委员会"
	}
]