[
	{
		"value":"420582102001",
		"name":"过街楼社区居委会"
	},
	{
		"value":"420582102200",
		"name":"三星寺村"
	},
	{
		"value":"420582102201",
		"name":"星火村委会"
	},
	{
		"value":"420582102202",
		"name":"赵湖村委会"
	},
	{
		"value":"420582102203",
		"name":"观基寺村委会"
	},
	{
		"value":"420582102204",
		"name":"前英村委会"
	},
	{
		"value":"420582102205",
		"name":"前进村委会"
	},
	{
		"value":"420582102206",
		"name":"前合村委会"
	},
	{
		"value":"420582102207",
		"name":"前华村委会"
	},
	{
		"value":"420582102208",
		"name":"郭家场村委会"
	},
	{
		"value":"420582102209",
		"name":"前程村委会"
	},
	{
		"value":"420582102210",
		"name":"民新村委会"
	},
	{
		"value":"420582102211",
		"name":"建国村委会"
	},
	{
		"value":"420582102212",
		"name":"民合村委会"
	},
	{
		"value":"420582102213",
		"name":"民耀村委会"
	},
	{
		"value":"420582102214",
		"name":"红联村委会"
	},
	{
		"value":"420582102215",
		"name":"红胜村委会"
	},
	{
		"value":"420582102216",
		"name":"红日村委会"
	},
	{
		"value":"420582102217",
		"name":"红明村委会"
	},
	{
		"value":"420582102218",
		"name":"丁场村委会"
	},
	{
		"value":"420582102219",
		"name":"官垱村委会"
	}
]