[
	{
		"value":"420704103001",
		"name":"武钢矿山机修居委会"
	},
	{
		"value":"420704103201",
		"name":"碧石村委会"
	},
	{
		"value":"420704103202",
		"name":"虹桥村委会"
	},
	{
		"value":"420704103203",
		"name":"黄咀村委会"
	},
	{
		"value":"420704103204",
		"name":"金盆村委会"
	},
	{
		"value":"420704103205",
		"name":"金文武村委会"
	},
	{
		"value":"420704103206",
		"name":"李边村委会"
	},
	{
		"value":"420704103207",
		"name":"李镜村委会"
	},
	{
		"value":"420704103208",
		"name":"卢湾村委会（长阳社区）"
	},
	{
		"value":"420704103209",
		"name":"农会山村委会"
	},
	{
		"value":"420704103210",
		"name":"樟术岭村委会"
	}
]