[
	{
		"value":"420704200201",
		"name":"保团村委会"
	},
	{
		"value":"420704200202",
		"name":"草陂村委会"
	},
	{
		"value":"420704200203",
		"name":"胡桥村委会"
	},
	{
		"value":"420704200204",
		"name":"黄山村委会"
	},
	{
		"value":"420704200205",
		"name":"加奖村委会"
	},
	{
		"value":"420704200206",
		"name":"牌楼村委会"
	},
	{
		"value":"420704200207",
		"name":"沙窝村委会"
	},
	{
		"value":"420704200208",
		"name":"新湾村委会"
	},
	{
		"value":"420704200209",
		"name":"渔坝村委会"
	},
	{
		"value":"420704200210",
		"name":"赵寨村委会"
	},
	{
		"value":"420704200211",
		"name":"走马村委会"
	}
]