[
	{
		"value":"421221106001",
		"name":"潘家湾社区居委会"
	},
	{
		"value":"421221106002",
		"name":"红光社区居委会"
	},
	{
		"value":"421221106200",
		"name":"潘家湾村民委员会"
	},
	{
		"value":"421221106201",
		"name":"肖家洲村民委员会"
	},
	{
		"value":"421221106202",
		"name":"四邑村民委员会"
	},
	{
		"value":"421221106203",
		"name":"羊毛岸村民委员会"
	},
	{
		"value":"421221106204",
		"name":"苍梧岭村民委员会"
	},
	{
		"value":"421221106205",
		"name":"老官咀村民委员会"
	},
	{
		"value":"421221106206",
		"name":"畈湖村民委员会"
	},
	{
		"value":"421221106207",
		"name":"东村村民委员会"
	},
	{
		"value":"421221106208",
		"name":"三湾村民委员会"
	},
	{
		"value":"421221106209",
		"name":"龙坎湖村民委员会"
	},
	{
		"value":"421221106210",
		"name":"官垱村民委员会"
	}
]