[
	{
		"value":"440117103001",
		"name":"温泉社区居委会"
	},
	{
		"value":"440117103002",
		"name":"龙岗社区居委会"
	},
	{
		"value":"440117103003",
		"name":"灌村社区居委会"
	},
	{
		"value":"440117103004",
		"name":"温泉河西社区居委会"
	},
	{
		"value":"440117103200",
		"name":"温泉村委会"
	},
	{
		"value":"440117103201",
		"name":"天湖村委会"
	},
	{
		"value":"440117103202",
		"name":"卫东村委会"
	},
	{
		"value":"440117103203",
		"name":"乌石村委会"
	},
	{
		"value":"440117103204",
		"name":"云星村委会"
	},
	{
		"value":"440117103205",
		"name":"宣星村委会"
	},
	{
		"value":"440117103206",
		"name":"源湖村委会"
	},
	{
		"value":"440117103207",
		"name":"乌土村委会"
	},
	{
		"value":"440117103208",
		"name":"龙岗村委会"
	},
	{
		"value":"440117103209",
		"name":"龙桥村委会"
	},
	{
		"value":"440117103210",
		"name":"平岗村委会"
	},
	{
		"value":"440117103211",
		"name":"中田村委会"
	},
	{
		"value":"440117103212",
		"name":"桃莲村委会"
	},
	{
		"value":"440117103213",
		"name":"密石村委会"
	},
	{
		"value":"440117103214",
		"name":"石海村委会"
	},
	{
		"value":"440117103215",
		"name":"石南村委会"
	},
	{
		"value":"440117103216",
		"name":"南星村委会"
	},
	{
		"value":"440117103217",
		"name":"新田村委会"
	},
	{
		"value":"440117103218",
		"name":"龙新村委会"
	},
	{
		"value":"440117103219",
		"name":"新南村委会"
	},
	{
		"value":"440117103220",
		"name":"南平村委会"
	},
	{
		"value":"440117103221",
		"name":"石坑村委会"
	}
]