[
	{
		"value":"440608004001",
		"name":"河江社区居委会"
	},
	{
		"value":"440608004002",
		"name":"庆洲社区居委会"
	},
	{
		"value":"440608004005",
		"name":"长安社区居委会"
	},
	{
		"value":"440608004007",
		"name":"中山社区居委会"
	},
	{
		"value":"440608004009",
		"name":"健力社区居委会"
	},
	{
		"value":"440608004010",
		"name":"竹园社区居委会"
	},
	{
		"value":"440608004012",
		"name":"岭南社区居委会"
	},
	{
		"value":"440608004014",
		"name":"金华社区居委会"
	},
	{
		"value":"440608004015",
		"name":"安泰社区居委会"
	},
	{
		"value":"440608004017",
		"name":"月明社区居委会"
	},
	{
		"value":"440608004019",
		"name":"育才社区居委会"
	},
	{
		"value":"440608004022",
		"name":"三洲社区居委会"
	},
	{
		"value":"440608004023",
		"name":"江湾社区居委会"
	},
	{
		"value":"440608004024",
		"name":"照明社区居委会"
	},
	{
		"value":"440608004025",
		"name":"泰华社区居委会"
	},
	{
		"value":"440608004026",
		"name":"明湖社区居委会"
	},
	{
		"value":"440608004202",
		"name":"罗西村委会"
	},
	{
		"value":"440608004203",
		"name":"孔堂村委会"
	},
	{
		"value":"440608004204",
		"name":"仙村村委会"
	},
	{
		"value":"440608004205",
		"name":"尼教村委会"
	},
	{
		"value":"440608004206",
		"name":"铁岗村委会"
	},
	{
		"value":"440608004207",
		"name":"伦埇村委会"
	},
	{
		"value":"440608004208",
		"name":"石洲村委会"
	},
	{
		"value":"440608004209",
		"name":"南洲村委会"
	},
	{
		"value":"440608004210",
		"name":"塘南村委会"
	},
	{
		"value":"440608004211",
		"name":"泰兴村委会"
	},
	{
		"value":"440608004212",
		"name":"泰和村委会"
	},
	{
		"value":"440608004213",
		"name":"范洲村委会"
	},
	{
		"value":"440608004214",
		"name":"王臣村委会"
	},
	{
		"value":"440608004215",
		"name":"阮埇村委会"
	},
	{
		"value":"440608004216",
		"name":"苏村村委会"
	}
]