[
	{
		"value":"451024105200",
		"name":"东凌村委会"
	},
	{
		"value":"451024105201",
		"name":"定坡村委会"
	},
	{
		"value":"451024105202",
		"name":"新屯村委会"
	},
	{
		"value":"451024105203",
		"name":"陇务村委会"
	},
	{
		"value":"451024105204",
		"name":"多莫村委会"
	},
	{
		"value":"451024105205",
		"name":"高国村委会"
	},
	{
		"value":"451024105206",
		"name":"陇桥村委会"
	},
	{
		"value":"451024105207",
		"name":"陇门村委会"
	},
	{
		"value":"451024105208",
		"name":"登限村委会"
	},
	{
		"value":"451024105209",
		"name":"朴圩村委会"
	},
	{
		"value":"451024105210",
		"name":"大福村委会"
	},
	{
		"value":"451024105211",
		"name":"多柏村委会"
	},
	{
		"value":"451024105212",
		"name":"中那村委会"
	},
	{
		"value":"451024105213",
		"name":"甘必村委会"
	},
	{
		"value":"451024105214",
		"name":"平交村委会"
	},
	{
		"value":"451024105215",
		"name":"那么村委会"
	},
	{
		"value":"451024105216",
		"name":"多俄村委会"
	},
	{
		"value":"451024105217",
		"name":"多脉村委会"
	},
	{
		"value":"451024105218",
		"name":"多乐村委会"
	}
]