[
	{
		"value":"451121105001",
		"name":"马江街居委会"
	},
	{
		"value":"451121105002",
		"name":"水运居委会"
	},
	{
		"value":"451121105201",
		"name":"熊埠村委会"
	},
	{
		"value":"451121105202",
		"name":"白梅村委会"
	},
	{
		"value":"451121105203",
		"name":"盘古村委会"
	},
	{
		"value":"451121105204",
		"name":"江塘村委会"
	},
	{
		"value":"451121105205",
		"name":"砂冲村委会"
	},
	{
		"value":"451121105206",
		"name":"古袍村委会"
	},
	{
		"value":"451121105207",
		"name":"新兴村委会"
	},
	{
		"value":"451121105208",
		"name":"湾岛村委会"
	},
	{
		"value":"451121105209",
		"name":"花罗村委会"
	},
	{
		"value":"451121105210",
		"name":"清洲村委会"
	},
	{
		"value":"451121105211",
		"name":"东旺村委会"
	},
	{
		"value":"451121105212",
		"name":"枫木村委会"
	},
	{
		"value":"451121105213",
		"name":"古岛村委会"
	},
	{
		"value":"451121105214",
		"name":"沙婆村委会"
	}
]