[
	{
		"value":"451421103001",
		"name":"柳桥社区居委会"
	},
	{
		"value":"451421103201",
		"name":"雷大村委会"
	},
	{
		"value":"451421103202",
		"name":"上屯村委会"
	},
	{
		"value":"451421103203",
		"name":"岜留村委会"
	},
	{
		"value":"451421103204",
		"name":"灶瓦村委会"
	},
	{
		"value":"451421103205",
		"name":"新村村委会"
	},
	{
		"value":"451421103206",
		"name":"渠齐村委会"
	},
	{
		"value":"451421103207",
		"name":"西长村委会"
	},
	{
		"value":"451421103208",
		"name":"扶岜村委会"
	},
	{
		"value":"451421103209",
		"name":"坡利村委会"
	},
	{
		"value":"451421103210",
		"name":"坡龛村委会"
	},
	{
		"value":"451421103211",
		"name":"平坡村委会"
	},
	{
		"value":"451421103212",
		"name":"那加村委会"
	}
]