[
	{
		"value":"469005115001",
		"name":"铺前墟社区居委会"
	},
	{
		"value":"469005115200",
		"name":"地太村委会"
	},
	{
		"value":"469005115201",
		"name":"东坡村委会"
	},
	{
		"value":"469005115202",
		"name":"林梧村委会"
	},
	{
		"value":"469005115203",
		"name":"隆丰村委会"
	},
	{
		"value":"469005115204",
		"name":"美港村委会"
	},
	{
		"value":"469005115205",
		"name":"铺港村委会"
	},
	{
		"value":"469005115206",
		"name":"铺龙村委会"
	},
	{
		"value":"469005115207",
		"name":"铺前村委会"
	},
	{
		"value":"469005115208",
		"name":"铺渔村委会"
	},
	{
		"value":"469005115209",
		"name":"七岭村委会"
	},
	{
		"value":"469005115210",
		"name":"仕后村委会"
	}
]