[
	{
		"value":"500106008001",
		"name":"经济桥社区居民委员会"
	},
	{
		"value":"500106008002",
		"name":"果园社区居民委员会"
	},
	{
		"value":"500106008003",
		"name":"松堡社区居民委员会"
	},
	{
		"value":"500106008004",
		"name":"柏杨村社区居民委员会"
	},
	{
		"value":"500106008005",
		"name":"江家院社区居民委员会"
	},
	{
		"value":"500106008010",
		"name":"美丽阳光家园社区居民委员会"
	},
	{
		"value":"500106008011",
		"name":"宏城名都社区居民委员会"
	},
	{
		"value":"500106008200",
		"name":"双碑村村民委员会"
	},
	{
		"value":"500106008201",
		"name":"南溪村村民委员会"
	},
	{
		"value":"500106008202",
		"name":"井口村村民委员会"
	},
	{
		"value":"500106008203",
		"name":"二塘村村民委员会"
	}
]