[
	{
		"value":"510623113001",
		"name":"笋竹垭社区居民委员会"
	},
	{
		"value":"510623113201",
		"name":"玉屏村村民委员会"
	},
	{
		"value":"510623113203",
		"name":"旭光村村民委员会"
	},
	{
		"value":"510623113204",
		"name":"团山村村民委员会"
	},
	{
		"value":"510623113206",
		"name":"望云村村民委员会"
	},
	{
		"value":"510623113208",
		"name":"囤粮村村民委员会"
	},
	{
		"value":"510623113210",
		"name":"凡龙村村民委员会"
	},
	{
		"value":"510623113211",
		"name":"长春村村民委员会"
	},
	{
		"value":"510623113213",
		"name":"金钩村村民委员会"
	},
	{
		"value":"510623113215",
		"name":"大石村村民委员会"
	}
]