[
	{
		"value":"510682108002",
		"name":"京什社区居民委员会"
	},
	{
		"value":"510682108003",
		"name":"白沙泉社区居民委员会"
	},
	{
		"value":"510682108004",
		"name":"双盛社区居民委员会"
	},
	{
		"value":"510682108201",
		"name":"静安村村民委员会"
	},
	{
		"value":"510682108203",
		"name":"邓通村村民委员会"
	},
	{
		"value":"510682108204",
		"name":"万缘村村民委员会"
	},
	{
		"value":"510682108205",
		"name":"东岳村村民委员会"
	},
	{
		"value":"510682108206",
		"name":"马祖村村民委员会"
	},
	{
		"value":"510682108207",
		"name":"复兴村村民委员会"
	},
	{
		"value":"510682108208",
		"name":"白鱼河村村民委员会"
	},
	{
		"value":"510682108209",
		"name":"东林村村民委员会"
	},
	{
		"value":"510682108210",
		"name":"涌麟村村民委员会"
	}
]