[
	{
		"value":"511503003002",
		"name":"学府社区居民委员会"
	},
	{
		"value":"511503003003",
		"name":"仙源社区居民委员会"
	},
	{
		"value":"511503003004",
		"name":"天泰社区居民委员会"
	},
	{
		"value":"511503003005",
		"name":"川主社区居民委员会"
	},
	{
		"value":"511503003006",
		"name":"江屿社区居民委员会"
	},
	{
		"value":"511503003201",
		"name":"滨江社区村民委员会"
	},
	{
		"value":"511503003202",
		"name":"金鸡社区村民委员会"
	},
	{
		"value":"511503003204",
		"name":"石岭村民委员会"
	},
	{
		"value":"511503003205",
		"name":"平安村民委员会"
	},
	{
		"value":"511503003206",
		"name":"石马社区村民委员会"
	},
	{
		"value":"511503003207",
		"name":"添丘村民委员会"
	},
	{
		"value":"511503003208",
		"name":"凤凰社区村民委员会"
	},
	{
		"value":"511503003209",
		"name":"洪桥社区村民委员会"
	},
	{
		"value":"511503003210",
		"name":"长江社区村民委员会"
	}
]