[
	{
		"value":"511528111001",
		"name":"三河口社区居民委员会"
	},
	{
		"value":"511528111201",
		"name":"金钟村民委员会"
	},
	{
		"value":"511528111206",
		"name":"民心村民委员会"
	},
	{
		"value":"511528111208",
		"name":"大同村民委员会"
	},
	{
		"value":"511528111211",
		"name":"踏水桥村民委员会"
	},
	{
		"value":"511528111212",
		"name":"同乐村民委员会"
	},
	{
		"value":"511528111216",
		"name":"长久村民委员会"
	},
	{
		"value":"511528111221",
		"name":"连心村民委员会"
	},
	{
		"value":"511528111222",
		"name":"长兴社区村民委员会"
	},
	{
		"value":"511528111224",
		"name":"连天山社区村民委员会"
	}
]