[
	{
		"value":"520527208002",
		"name":"响水社区居民委员会"
	},
	{
		"value":"520527208006",
		"name":"坪子社区"
	},
	{
		"value":"520527208204",
		"name":"联盟村委会"
	},
	{
		"value":"520527208205",
		"name":"中井村委会"
	},
	{
		"value":"520527208208",
		"name":"高原村委会"
	},
	{
		"value":"520527208209",
		"name":"处卓村委会"
	},
	{
		"value":"520527208210",
		"name":"河山村委会"
	},
	{
		"value":"520527208211",
		"name":"铁匠村民委员会"
	},
	{
		"value":"520527208212",
		"name":"联合村民委员会"
	},
	{
		"value":"520527208213",
		"name":"共同村民委员会"
	},
	{
		"value":"520527208214",
		"name":"沿海村民委员会"
	}
]