[
	{
		"value":"522629107001",
		"name":"久仰社区"
	},
	{
		"value":"522629107201",
		"name":"党义村委会"
	},
	{
		"value":"522629107202",
		"name":"基佑村委会"
	},
	{
		"value":"522629107205",
		"name":"久丢村委会"
	},
	{
		"value":"522629107206",
		"name":"久顺村委会"
	},
	{
		"value":"522629107211",
		"name":"巫溜村委会"
	},
	{
		"value":"522629107217",
		"name":"夭那村委会"
	},
	{
		"value":"522629107218",
		"name":"巫交村委会"
	},
	{
		"value":"522629107221",
		"name":"久敢村委会"
	},
	{
		"value":"522629107225",
		"name":"巫仰村委会"
	},
	{
		"value":"522629107227",
		"name":"久甲村委会"
	},
	{
		"value":"522629107228",
		"name":"久吉村委会"
	},
	{
		"value":"522629107229",
		"name":"摆伟村委会"
	},
	{
		"value":"522629107230",
		"name":"江北村委会"
	},
	{
		"value":"522629107231",
		"name":"党里村委会"
	},
	{
		"value":"522629107232",
		"name":"东凤村委会"
	},
	{
		"value":"522629107233",
		"name":"党峰村委会"
	}
]