[
	{
		"value":"530181003001",
		"name":"八街社区居委会"
	},
	{
		"value":"530181003201",
		"name":"八街村委会"
	},
	{
		"value":"530181003202",
		"name":"招霸村委会"
	},
	{
		"value":"530181003203",
		"name":"鸣凤村委会"
	},
	{
		"value":"530181003204",
		"name":"铁厂村委会"
	},
	{
		"value":"530181003205",
		"name":"堍杉村委会"
	},
	{
		"value":"530181003206",
		"name":"凤仪村委会"
	},
	{
		"value":"530181003207",
		"name":"枧槽营村委会"
	},
	{
		"value":"530181003208",
		"name":"朝阳村委会"
	},
	{
		"value":"530181003209",
		"name":"中所村委会"
	},
	{
		"value":"530181003210",
		"name":"二街村委会"
	},
	{
		"value":"530181003211",
		"name":"窑坡村委会"
	},
	{
		"value":"530181003212",
		"name":"摩所营村委会"
	},
	{
		"value":"530181003213",
		"name":"一六村委会"
	},
	{
		"value":"530181003214",
		"name":"吴里坝村委会"
	},
	{
		"value":"530181003215",
		"name":"七街村委会"
	},
	{
		"value":"530181003216",
		"name":"温水村委会"
	},
	{
		"value":"530181003217",
		"name":"大营村委会"
	},
	{
		"value":"530181003218",
		"name":"五岳村委会"
	},
	{
		"value":"530181003219",
		"name":"龙洞村委会"
	},
	{
		"value":"530181003220",
		"name":"磨南德村委会"
	},
	{
		"value":"530181003221",
		"name":"相连村委会"
	}
]