[
	{
		"value":"532501001001",
		"name":"青杉里社区居委会"
	},
	{
		"value":"532501001002",
		"name":"宝华社区居委会"
	},
	{
		"value":"532501001003",
		"name":"胜利社区居委会"
	},
	{
		"value":"532501001004",
		"name":"文锡社区居委会"
	},
	{
		"value":"532501001005",
		"name":"民权社区居委会"
	},
	{
		"value":"532501001006",
		"name":"上河社区居委会"
	},
	{
		"value":"532501001007",
		"name":"永胜社区居委会"
	},
	{
		"value":"532501001008",
		"name":"和平社区居委会"
	},
	{
		"value":"532501001009",
		"name":"绿海社区居委会"
	},
	{
		"value":"532501001011",
		"name":"中山社区居委会"
	},
	{
		"value":"532501001012",
		"name":"五一社区居委会"
	},
	{
		"value":"532501001014",
		"name":"金湖南社区居委会"
	},
	{
		"value":"532501001016",
		"name":"新冠社区居委会"
	},
	{
		"value":"532501001017",
		"name":"建设社区居委会"
	},
	{
		"value":"532501001018",
		"name":"新电社区居委会"
	},
	{
		"value":"532501001019",
		"name":"云锡建安社区居委会"
	},
	{
		"value":"532501001020",
		"name":"云锡炼厂社区居委会"
	},
	{
		"value":"532501001021",
		"name":"云锡机厂社区居委会"
	},
	{
		"value":"532501001022",
		"name":"明珠社区居委会"
	},
	{
		"value":"532501001023",
		"name":"金湖西社区居委会"
	},
	{
		"value":"532501001024",
		"name":"云锡供水厂社区居委会"
	},
	{
		"value":"532501001025",
		"name":"金湖东社区居委会"
	},
	{
		"value":"532501001026",
		"name":"云锡机关社区居委会"
	},
	{
		"value":"532501001027",
		"name":"三零八队社区居委会"
	},
	{
		"value":"532501001028",
		"name":"云锡储运社区居委会"
	},
	{
		"value":"532501001030",
		"name":"锡山社区居委会"
	}
]