[
	{
		"value":"540323100",
		"name":"类乌齐镇"
	},
	{
		"value":"540323100",
		"name":"类乌齐镇"
	},
	{
		"value":"540323101",
		"name":"桑多镇"
	},
	{
		"value":"540323101",
		"name":"桑多镇"
	},
	{
		"value":"540323200",
		"name":"甲桑卡乡"
	},
	{
		"value":"540323200",
		"name":"甲桑卡乡"
	},
	{
		"value":"540323201",
		"name":"长毛岭乡"
	},
	{
		"value":"540323201",
		"name":"长毛岭乡"
	},
	{
		"value":"540323202",
		"name":"岗色乡"
	},
	{
		"value":"540323202",
		"name":"岗色乡"
	},
	{
		"value":"540323203",
		"name":"吉多乡"
	},
	{
		"value":"540323203",
		"name":"吉多乡"
	},
	{
		"value":"540323204",
		"name":"宾达乡"
	},
	{
		"value":"540323204",
		"name":"宾达乡"
	},
	{
		"value":"540323205",
		"name":"卡玛多乡"
	},
	{
		"value":"540323205",
		"name":"卡玛多乡"
	},
	{
		"value":"540323206",
		"name":"尚卡乡"
	},
	{
		"value":"540323206",
		"name":"尚卡乡"
	},
	{
		"value":"540323207",
		"name":"伊日乡"
	},
	{
		"value":"540323207",
		"name":"伊日乡"
	}
]