[
	{
		"value":"610122104001",
		"name":"汤泉社区"
	},
	{
		"value":"610122104200",
		"name":"塘子街村委会"
	},
	{
		"value":"610122104201",
		"name":"石门村委会"
	},
	{
		"value":"610122104202",
		"name":"联丰村委会"
	},
	{
		"value":"610122104207",
		"name":"洪寨村委会"
	},
	{
		"value":"610122104208",
		"name":"马塬村委会"
	},
	{
		"value":"610122104209",
		"name":"薛庙村委会"
	},
	{
		"value":"610122104210",
		"name":"张坡村委会"
	},
	{
		"value":"610122104213",
		"name":"高堡村委会"
	},
	{
		"value":"610122104214",
		"name":"尖角村委会"
	},
	{
		"value":"610122104226",
		"name":"田家村委会"
	},
	{
		"value":"610122104227",
		"name":"敬家村委会"
	},
	{
		"value":"610122104228",
		"name":"龚家村委会"
	},
	{
		"value":"610122104229",
		"name":"柿园子村委会"
	},
	{
		"value":"610122104230",
		"name":"侯家村委会"
	},
	{
		"value":"610122104231",
		"name":"小寺村委会"
	},
	{
		"value":"610122104232",
		"name":"史家寨村委会"
	},
	{
		"value":"610122104240",
		"name":"东山村委会"
	},
	{
		"value":"610122104241",
		"name":"骆驼岭村委会"
	},
	{
		"value":"610122104242",
		"name":"汤峪河村委会"
	},
	{
		"value":"610122104243",
		"name":"河东村委会"
	},
	{
		"value":"610122104244",
		"name":"峙峪村委会"
	},
	{
		"value":"610122104245",
		"name":"汤石村"
	},
	{
		"value":"610122104246",
		"name":"聚庆村委会"
	},
	{
		"value":"610122104247",
		"name":"肖家坡村委会"
	},
	{
		"value":"610122104248",
		"name":"孙家坡村委会"
	},
	{
		"value":"610122104249",
		"name":"姚林寨村委会"
	}
]