[
	{
		"value":"610924108001",
		"name":"街道社区居委会"
	},
	{
		"value":"610924108002",
		"name":"西河社区居委会"
	},
	{
		"value":"610924108200",
		"name":"双河村委会"
	},
	{
		"value":"610924108201",
		"name":"庄房村委会"
	},
	{
		"value":"610924108202",
		"name":"东垭村委会"
	},
	{
		"value":"610924108203",
		"name":"中良村委会"
	},
	{
		"value":"610924108205",
		"name":"解放村委会"
	},
	{
		"value":"610924108207",
		"name":"莲花村委会"
	},
	{
		"value":"610924108208",
		"name":"四坪村委会"
	},
	{
		"value":"610924108209",
		"name":"苗河村委会"
	},
	{
		"value":"610924108211",
		"name":"取宝村委会"
	},
	{
		"value":"610924108214",
		"name":"六河村委会"
	}
]