[
	{
		"value":"620821110200",
		"name":"三星村民委员会"
	},
	{
		"value":"620821110201",
		"name":"红崖湾村民委员会"
	},
	{
		"value":"620821110202",
		"name":"何家村民委员会"
	},
	{
		"value":"620821110203",
		"name":"周家村民委员会"
	},
	{
		"value":"620821110204",
		"name":"寨子洼村民委员会"
	},
	{
		"value":"620821110205",
		"name":"四郞殿村民委员会"
	},
	{
		"value":"620821110206",
		"name":"口家村民委员会"
	},
	{
		"value":"620821110207",
		"name":"崖窑村民委员会"
	},
	{
		"value":"620821110208",
		"name":"七千关村民委员会"
	},
	{
		"value":"620821110209",
		"name":"荒场村民委员会"
	},
	{
		"value":"620821110210",
		"name":"盘口村民委员会"
	},
	{
		"value":"620821110211",
		"name":"焦村村民委员会"
	},
	{
		"value":"620821110212",
		"name":"朱家沟村村民委员会"
	},
	{
		"value":"620821110213",
		"name":"里口村民委员会"
	},
	{
		"value":"620821110214",
		"name":"阴坡村民委员会"
	}
]