[
	{
		"value":"621223110200",
		"name":"两河口村村民委员会"
	},
	{
		"value":"621223110201",
		"name":"清水子村村民委员会"
	},
	{
		"value":"621223110202",
		"name":"曹下村村民委员会"
	},
	{
		"value":"621223110203",
		"name":"麻地坪村村民委员会"
	},
	{
		"value":"621223110204",
		"name":"桃坪村村民委员会"
	},
	{
		"value":"621223110205",
		"name":"柯门道村村民委员会"
	},
	{
		"value":"621223110206",
		"name":"庙下村村民委员会"
	},
	{
		"value":"621223110207",
		"name":"王院村村民委员会"
	},
	{
		"value":"621223110208",
		"name":"羊古堆村村民委员会"
	},
	{
		"value":"621223110209",
		"name":"四方村村民委员会"
	},
	{
		"value":"621223110210",
		"name":"寨子村村民委员会"
	},
	{
		"value":"621223110211",
		"name":"化马村村民委员会"
	},
	{
		"value":"621223110212",
		"name":"新声村村民委员会"
	},
	{
		"value":"621223110213",
		"name":"罗湾村村民委员会"
	},
	{
		"value":"621223110214",
		"name":"石院村村民委员会"
	},
	{
		"value":"621223110215",
		"name":"街上村村民委员会"
	},
	{
		"value":"621223110216",
		"name":"山背村村民委员会"
	}
]